.gitignore
.pre-commit-config.yaml
CHANGELOG.md
LICENSE
README.md
pyproject.toml
requirements.txt
setup.cfg
setup.py
Tasker/__init__.py
Tasker/__main__.py
Tasker/__version__.py
Tasker/cli.py
Tasker/common.py
Tasker/inspector.py
Tasker/operations.py
Tasker/parser.py
Tasker/parser_test.py
Tasker/templater.py
Tasker/types.py
pyTasker.egg-info/PKG-INFO
pyTasker.egg-info/SOURCES.txt
pyTasker.egg-info/dependency_links.txt
pyTasker.egg-info/entry_points.txt
pyTasker.egg-info/requires.txt
pyTasker.egg-info/top_level.txt
static/Copy PDFs then zip.png
static/Copy PDFs.png