Metadata-Version: 2.1
Name: pyTasker
Version: 0.6.7
Summary: Run pipelines on your own computer for better automation
Home-page: https://github.com/carlossilva2/pyTasker
Author: Carlos Silva
Author-email: carlos.miguel.silva@protonmail.com
License: GPLv3
Project-URL: Source, https://github.com/carlossilva2/pyTasker
Project-URL: Documentation, https://cmsilva.gitbook.io/pytasker/
Platform: UNKNOWN
Classifier: Development Status :: 4 - Beta
Classifier: Environment :: Console
Classifier: Intended Audience :: Developers
Classifier: License :: OSI Approved :: GNU General Public License v3 (GPLv3)
Classifier: Natural Language :: English
Classifier: Operating System :: OS Independent
Classifier: Programming Language :: Python :: 3
Classifier: Programming Language :: Python :: 3.8
Classifier: Programming Language :: Python :: 3.9
Classifier: Programming Language :: Python :: 3.10
Classifier: Topic :: Software Development
Classifier: Typing :: Typed
Requires-Python: >=3.8
License-File: LICENSE
